[
  {
    "group": "BTS",
    "release_title": "DARK&WILD",
    "release_date": "2014-08-20",
    "stream": "album",
    "title_tracks": [
      "Danger"
    ],
    "youtube_video_url": "https://www.youtube.com/watch?v=43r6lXilbcQ",
    "youtube_video_provenance": "migration-critical first slice official MV URL"
  },
  {
    "group": "BTS",
    "release_title": "화양연화 pt.1",
    "release_date": "2015-04-29",
    "stream": "album",
    "title_tracks": [
      "I NEED U"
    ],
    "youtube_video_url": "https://www.youtube.com/watch?v=jjskoRh8GTE",
    "youtube_video_provenance": "migration-critical first slice official MV URL"
  },
  {
    "group": "BTS",
    "release_title": "LOVE YOURSELF 承 ‘Her’",
    "release_date": "2017-04-10",
    "stream": "album",
    "title_tracks": [
      "DNA"
    ],
    "youtube_video_url": "https://www.youtube.com/watch?v=MBdVXkSdhwU",
    "youtube_video_provenance": "migration-critical first slice official MV URL"
  },
  {
    "group": "BTS",
    "release_title": "LOVE YOURSELF 轉 ‘Tear’",
    "release_date": "2018-05-18",
    "stream": "album",
    "title_tracks": [
      "FAKE LOVE"
    ],
    "youtube_video_url": "https://www.youtube.com/watch?v=7C2z4GqqS5E",
    "youtube_video_provenance": "migration-critical first slice official MV URL"
  },
  {
    "group": "BTS",
    "release_title": "MAP OF THE SOUL : PERSONA",
    "release_date": "2019-04-12",
    "stream": "album",
    "title_tracks": [
      "작은 것들을 위한 시 (Boy With Luv)"
    ],
    "youtube_video_url": "https://www.youtube.com/watch?v=XsX3ATc3FbA",
    "youtube_video_provenance": "migration-critical first slice official MV URL"
  },
  {
    "group": "BLACKPINK",
    "release_title": "SQUARE UP",
    "release_date": "2018-06-15",
    "stream": "album",
    "title_tracks": [
      "뚜두뚜두 (DDU-DU DDU-DU)"
    ],
    "youtube_video_url": "https://www.youtube.com/watch?v=IHNzOHi8sJs",
    "youtube_video_provenance": "migration-critical first slice official MV URL"
  },
  {
    "group": "TWICE",
    "release_title": "THE STORY BEGINS",
    "release_date": "2015-10-20",
    "stream": "album",
    "title_tracks": [
      "OOH-AHH하게"
    ],
    "youtube_video_url": "https://www.youtube.com/watch?v=0rtV5esQT6I",
    "youtube_video_provenance": "migration-critical first slice official MV URL"
  },
  {
    "group": "TWICE",
    "release_title": "PAGE TWO",
    "release_date": "2016-04-25",
    "stream": "album",
    "title_tracks": [
      "CHEER UP"
    ],
    "youtube_video_url": "https://www.youtube.com/watch?v=c7rCyll5AeY",
    "youtube_video_provenance": "migration-critical first slice official MV URL"
  },
  {
    "group": "TWICE",
    "release_title": "TWICEcoaster : LANE 1",
    "release_date": "2016-10-24",
    "stream": "album",
    "title_tracks": [
      "TT"
    ],
    "youtube_video_url": "https://www.youtube.com/watch?v=ePpPVE-GGJw",
    "youtube_video_provenance": "migration-critical first slice official MV URL"
  },
  {
    "group": "TWICE",
    "release_title": "twicetagram",
    "release_date": "2017-10-30",
    "stream": "album",
    "title_tracks": [
      "LIKEY"
    ],
    "youtube_video_url": "https://www.youtube.com/watch?v=V2hlQkVJZhE",
    "youtube_video_provenance": "migration-critical first slice official MV URL"
  },
  {
    "group": "TWICE",
    "release_title": "Eyes wide open",
    "release_date": "2020-10-26",
    "stream": "album",
    "title_tracks": [
      "I CAN'T STOP ME"
    ],
    "youtube_video_url": "https://www.youtube.com/watch?v=CM4CkVFmTds",
    "youtube_video_provenance": "migration-critical first slice official MV URL"
  },
  {
    "group": "SEVENTEEN",
    "release_title": "17 CARAT",
    "release_date": "2015-05-29",
    "stream": "album",
    "title_tracks": [
      "아낀다"
    ],
    "youtube_video_url": "https://www.youtube.com/watch?v=9rUFQJrCT7M",
    "youtube_video_provenance": "migration-critical first slice official MV URL"
  },
  {
    "group": "SEVENTEEN",
    "release_title": "BOYS BE",
    "release_date": "2015-09-10",
    "stream": "album",
    "title_tracks": [
      "만세"
    ],
    "youtube_video_url": "https://www.youtube.com/watch?v=9M7k9ZV67c0",
    "youtube_video_provenance": "migration-critical first slice official MV URL"
  },
  {
    "group": "SEVENTEEN",
    "release_title": "TEEN, AGE",
    "release_date": "2017-11-06",
    "stream": "album",
    "title_tracks": [
      "박수"
    ],
    "youtube_video_url": "https://www.youtube.com/watch?v=CyzEtbG-sxY",
    "youtube_video_provenance": "migration-critical first slice official MV URL"
  },
  {
    "group": "SHINee",
    "release_title": "Romeo",
    "release_date": "2009-05-18",
    "stream": "album",
    "title_tracks": [
      "Juliette"
    ],
    "youtube_video_url": "https://www.youtube.com/watch?v=XwkP3qfwqs8",
    "youtube_video_provenance": "migration-critical first slice official MV URL"
  },
  {
    "group": "SHINee",
    "release_title": "2009, Year of Us",
    "release_date": "2009-10-19",
    "stream": "album",
    "title_tracks": [
      "Ring Ding Dong"
    ],
    "youtube_video_url": "https://www.youtube.com/watch?v=roughtzsCDI",
    "youtube_video_provenance": "migration-critical first slice official MV URL"
  },
  {
    "group": "SHINee",
    "release_title": "Odd",
    "release_date": "2015-05-18",
    "stream": "album",
    "title_tracks": [
      "View"
    ],
    "youtube_video_url": "https://www.youtube.com/watch?v=UF53cptEE5k",
    "youtube_video_provenance": "migration-critical first slice official MV URL"
  },
  {
    "group": "SHINee",
    "release_title": "The Story of Light EP.1",
    "release_date": "2018-05-28",
    "stream": "album",
    "title_tracks": [
      "Good Evening"
    ],
    "youtube_video_url": "https://www.youtube.com/watch?v=7dGwk5-QMpc",
    "youtube_video_provenance": "migration-critical first slice official MV URL"
  }
]
