{
  "meta": {
    "request_id": "bridge-release-detail-bridge-release-65b7172b"
  },
  "data": {
    "release": {
      "release_id": "bridge-release-65b7172b",
      "release_title": "Prelude of Love Chapter 2. ‘Growing Pains’",
      "release_date": "2023-04-26",
      "stream": "album",
      "release_kind": "ep"
    },
    "artwork": {
      "cover_image_url": "https://coverartarchive.org/release-group/4cbc72c4-49f2-4d35-b9af-cfc012400d7d/front",
      "thumbnail_image_url": "https://coverartarchive.org/release-group/4cbc72c4-49f2-4d35-b9af-cfc012400d7d/front-250",
      "artwork_source_type": "cover_art_archive",
      "artwork_source_url": "https://coverartarchive.org/release-group/4cbc72c4-49f2-4d35-b9af-cfc012400d7d"
    },
    "service_links": {
      "spotify": {
        "url": "https://open.spotify.com/album/7c4HuyVRABrlh7eOdhozwd"
      },
      "youtube_music": {
        "url": null
      }
    },
    "tracks": [
      {
        "order": 1,
        "title": "My Darling",
        "is_title_track": false
      },
      {
        "order": 2,
        "title": "Sunshower",
        "is_title_track": false
      },
      {
        "order": 3,
        "title": "Goodbye, My First Love",
        "is_title_track": false
      },
      {
        "order": 4,
        "title": "SKYLINE",
        "is_title_track": false
      }
    ],
    "mv": {
      "url": null,
      "video_id": null,
      "status": "unresolved",
      "provenance": "releaseHistory.placeholder_seed"
    },
    "notes": "Historical release-detail seed generated from releaseHistory.json. Detailed track and service metadata remain unresolved. MusicBrainz acquisition enriched: tracks, spotify_url (musicbrainz.release_group_release)."
  }
}
