{
  "meta": {
    "request_id": "bridge-release-detail-bridge-release-a346d7d2"
  },
  "data": {
    "release": {
      "release_id": "bridge-release-a346d7d2",
      "release_title": "Reload",
      "release_date": "2020-04-29",
      "stream": "album",
      "release_kind": "ep"
    },
    "artwork": null,
    "service_links": {
      "spotify": {
        "url": "https://open.spotify.com/album/1V5ilz8ghPl1PZJA1hbw3r"
      },
      "youtube_music": {
        "url": null
      }
    },
    "tracks": [
      {
        "order": 1,
        "title": "Ridin'",
        "is_title_track": false
      },
      {
        "order": 2,
        "title": "Quiet Down",
        "is_title_track": false
      },
      {
        "order": 3,
        "title": "7 Days",
        "is_title_track": false
      },
      {
        "order": 4,
        "title": "Love Again",
        "is_title_track": false
      },
      {
        "order": 5,
        "title": "Puzzle Piece",
        "is_title_track": false
      }
    ],
    "mv": {
      "url": null,
      "video_id": null,
      "status": "unresolved",
      "provenance": "releaseHistory.placeholder_seed"
    },
    "notes": "Historical release-detail seed generated from releaseHistory.json. Detailed track and service metadata remain unresolved. MusicBrainz acquisition enriched: tracks, spotify_url (musicbrainz.release_group_release)."
  }
}
