{
  "meta": {
    "request_id": "bridge-release-detail-bridge-release-338d0dc1"
  },
  "data": {
    "release": {
      "release_id": "bridge-release-338d0dc1",
      "release_title": "Every DAY6 September",
      "release_date": "2017-09-06",
      "stream": "song",
      "release_kind": "single"
    },
    "artwork": {
      "cover_image_url": "https://coverartarchive.org/release-group/b51bc057-c07f-409a-8d7e-10c7a37c56e8/front",
      "thumbnail_image_url": "https://coverartarchive.org/release-group/b51bc057-c07f-409a-8d7e-10c7a37c56e8/front-250",
      "artwork_source_type": "cover_art_archive",
      "artwork_source_url": "https://coverartarchive.org/release-group/b51bc057-c07f-409a-8d7e-10c7a37c56e8"
    },
    "service_links": {
      "spotify": {
        "url": null
      },
      "youtube_music": {
        "url": null
      }
    },
    "tracks": [
      {
        "order": 1,
        "title": "I Loved You",
        "is_title_track": false
      },
      {
        "order": 2,
        "title": "남겨둘게",
        "is_title_track": false
      }
    ],
    "mv": {
      "url": null,
      "video_id": null,
      "status": "unresolved",
      "provenance": "releaseHistory.placeholder_seed"
    },
    "notes": "Historical release-detail seed generated from releaseHistory.json. Detailed track and service metadata remain unresolved. MusicBrainz acquisition enriched: tracks (musicbrainz.release_group_release)."
  }
}
