{
  "meta": {
    "request_id": "bridge-release-detail-bridge-release-e8e5c75f"
  },
  "data": {
    "release": {
      "release_id": "bridge-release-e8e5c75f",
      "release_title": "BUFF",
      "release_date": "2024-03-13",
      "stream": "album",
      "release_kind": "ep"
    },
    "artwork": {
      "cover_image_url": "https://coverartarchive.org/release-group/33c2adb3-e57f-4ed0-b2cd-ce0be79e89eb/front",
      "thumbnail_image_url": "https://coverartarchive.org/release-group/33c2adb3-e57f-4ed0-b2cd-ce0be79e89eb/front-250",
      "artwork_source_type": "cover_art_archive",
      "artwork_source_url": "https://coverartarchive.org/release-group/33c2adb3-e57f-4ed0-b2cd-ce0be79e89eb"
    },
    "service_links": {
      "spotify": {
        "url": "https://open.spotify.com/album/5ppQCaEkY3k6ApwuWr0S39"
      },
      "youtube_music": {
        "url": null
      }
    },
    "tracks": [
      {
        "order": 1,
        "title": "MON2SUN (MON♡SUN)",
        "is_title_track": false
      },
      {
        "order": 2,
        "title": "SUPER POWER",
        "is_title_track": false
      },
      {
        "order": 3,
        "title": "GOT THE RIZZ",
        "is_title_track": false
      },
      {
        "order": 4,
        "title": "PASTEL",
        "is_title_track": false
      },
      {
        "order": 5,
        "title": "Now",
        "is_title_track": false
      },
      {
        "order": 6,
        "title": "SUPER POWER (English ver.)",
        "is_title_track": false
      }
    ],
    "mv": {
      "url": null,
      "video_id": null,
      "status": "unresolved",
      "provenance": "releaseHistory.placeholder_seed"
    },
    "notes": "Historical release-detail seed generated from releaseHistory.json. Detailed track and service metadata remain unresolved. MusicBrainz acquisition enriched: tracks, spotify_url (musicbrainz.release_group_release)."
  }
}
