{
  "meta": {
    "request_id": "bridge-release-detail-bridge-release-26f79289"
  },
  "data": {
    "release": {
      "release_id": "bridge-release-26f79289",
      "release_title": "DIM ∞",
      "release_date": "2025-04-01",
      "stream": "song",
      "release_kind": "single"
    },
    "artwork": {
      "cover_image_url": "https://coverartarchive.org/release-group/18523d88-13f8-4015-a0a2-fe3aa79ff470/front",
      "thumbnail_image_url": "https://coverartarchive.org/release-group/18523d88-13f8-4015-a0a2-fe3aa79ff470/front-250",
      "artwork_source_type": "cover_art_archive",
      "artwork_source_url": "https://coverartarchive.org/release-group/18523d88-13f8-4015-a0a2-fe3aa79ff470"
    },
    "service_links": {
      "spotify": {
        "url": "https://open.spotify.com/album/7FnEL1BCbrNeAwbBABcSl0"
      },
      "youtube_music": {
        "url": null
      }
    },
    "tracks": [
      {
        "order": 1,
        "title": "DIM",
        "is_title_track": true
      },
      {
        "order": 2,
        "title": "DIM (Nostalgic Edit)",
        "is_title_track": false
      },
      {
        "order": 3,
        "title": "DIM (Slowed)",
        "is_title_track": false
      },
      {
        "order": 4,
        "title": "DIM (Sped Up)",
        "is_title_track": false
      },
      {
        "order": 5,
        "title": "DIM (Fade)",
        "is_title_track": false
      }
    ],
    "mv": {
      "url": null,
      "video_id": null,
      "status": "unresolved",
      "provenance": "releaseHistory.placeholder_seed"
    },
    "notes": "Historical release-detail seed generated from releaseHistory.json. Detailed track and service metadata remain unresolved. MusicBrainz acquisition enriched: tracks, spotify_url (musicbrainz.release_group_release)."
  }
}
