{
  "meta": {
    "request_id": "bridge-release-detail-bridge-release-f0f4530a"
  },
  "data": {
    "release": {
      "release_id": "bridge-release-f0f4530a",
      "release_title": "TWICEcoaster : LANE 1",
      "release_date": "2016-10-24",
      "stream": "album",
      "release_kind": "ep"
    },
    "artwork": null,
    "service_links": {
      "spotify": {
        "url": "https://open.spotify.com/album/56w7UaxCFwsRr5VVk0agy0"
      },
      "youtube_music": {
        "url": null
      }
    },
    "tracks": [
      {
        "order": 1,
        "title": "TT",
        "is_title_track": false
      },
      {
        "order": 2,
        "title": "1 TO 10",
        "is_title_track": false
      },
      {
        "order": 3,
        "title": "PONYTAIL",
        "is_title_track": false
      },
      {
        "order": 4,
        "title": "JELLY JELLY",
        "is_title_track": false
      },
      {
        "order": 5,
        "title": "PIT‐A‐PAT",
        "is_title_track": false
      },
      {
        "order": 6,
        "title": "NEXT PAGE",
        "is_title_track": false
      },
      {
        "order": 7,
        "title": "ONE IN A MILLION",
        "is_title_track": false
      }
    ],
    "mv": {
      "url": null,
      "video_id": null,
      "status": "unresolved",
      "provenance": "releaseHistory.placeholder_seed"
    },
    "notes": "Historical release-detail seed generated from releaseHistory.json. Detailed track and service metadata remain unresolved. MusicBrainz acquisition enriched: tracks, spotify_url (musicbrainz.release_group_release)."
  }
}
