{
  "meta": {
    "request_id": "bridge-release-detail-bridge-release-dd1bb909"
  },
  "data": {
    "release": {
      "release_id": "bridge-release-dd1bb909",
      "release_title": "Keep It Sexy (MOMMAE 2)",
      "release_date": "2025-05-23",
      "stream": "song",
      "release_kind": "single"
    },
    "artwork": null,
    "service_links": {
      "spotify": {
        "url": "https://open.spotify.com/album/74Xun3jkHLajFFz2ymcsRs"
      },
      "youtube_music": {
        "url": null
      }
    },
    "tracks": [
      {
        "order": 1,
        "title": "Keep It Sexy (MOMMAE 2)",
        "is_title_track": true
      }
    ],
    "mv": {
      "url": null,
      "video_id": null,
      "status": "unresolved",
      "provenance": "releaseHistory.placeholder_seed"
    },
    "notes": "Historical release-detail seed generated from releaseHistory.json. Detailed track and service metadata remain unresolved. MusicBrainz acquisition enriched: tracks, spotify_url (musicbrainz.release_group_release)."
  }
}
