{
  "meta": {
    "request_id": "bridge-release-detail-bridge-release-d659858e"
  },
  "data": {
    "release": {
      "release_id": "bridge-release-d659858e",
      "release_title": "Down for you",
      "release_date": "2024-12-23",
      "stream": "song",
      "release_kind": "single"
    },
    "artwork": {
      "cover_image_url": "https://coverartarchive.org/release-group/f4beccb3-b729-472d-9157-285664610b9e/front",
      "thumbnail_image_url": "https://coverartarchive.org/release-group/f4beccb3-b729-472d-9157-285664610b9e/front-250",
      "artwork_source_type": "cover_art_archive",
      "artwork_source_url": "https://coverartarchive.org/release-group/f4beccb3-b729-472d-9157-285664610b9e"
    },
    "service_links": {
      "spotify": {
        "url": "https://open.spotify.com/album/4GQkIyzKxvXwJLtU91Vd2t"
      },
      "youtube_music": {
        "url": null
      }
    },
    "tracks": [
      {
        "order": 1,
        "title": "Down for you",
        "is_title_track": true
      }
    ],
    "mv": {
      "url": null,
      "video_id": null,
      "status": "unresolved",
      "provenance": "releaseHistory.placeholder_seed"
    },
    "notes": "Historical release-detail seed generated from releaseHistory.json. Detailed track and service metadata remain unresolved. MusicBrainz acquisition enriched: tracks, spotify_url (musicbrainz.release_group_release)."
  }
}
