{
  "meta": {
    "request_id": "bridge-release-detail-bridge-release-1ddb6fe8"
  },
  "data": {
    "release": {
      "release_id": "bridge-release-1ddb6fe8",
      "release_title": "Make It Right",
      "release_date": "2019-10-18",
      "stream": "song",
      "release_kind": "single"
    },
    "artwork": {
      "cover_image_url": "https://coverartarchive.org/release-group/f01f5615-a28c-4957-a642-3f5e87601d2b/front",
      "thumbnail_image_url": "https://coverartarchive.org/release-group/f01f5615-a28c-4957-a642-3f5e87601d2b/front-250",
      "artwork_source_type": "cover_art_archive",
      "artwork_source_url": "https://coverartarchive.org/release-group/f01f5615-a28c-4957-a642-3f5e87601d2b"
    },
    "service_links": {
      "spotify": {
        "url": "https://open.spotify.com/album/0ZI6Q1QJSYdeEQPvKzX1XR"
      },
      "youtube_music": {
        "url": null
      }
    },
    "tracks": [
      {
        "order": 1,
        "title": "Make It Right",
        "is_title_track": true
      }
    ],
    "mv": {
      "url": "https://www.youtube.com/watch?v=eXBu09fwe3I",
      "video_id": "eXBu09fwe3I",
      "status": "manual_override",
      "provenance": "youtube search auto-accepted via allowlist/title/date/view scoring"
    },
    "notes": "Historical release-detail seed generated from releaseHistory.json. Detailed track and service metadata remain unresolved. MusicBrainz acquisition enriched: tracks, spotify_url (musicbrainz.release_group_release). Canonical YouTube MV preserved from release_detail_overrides.json (youtube search auto-accepted via allowlist/title/date/view scoring)."
  }
}
